Workbook

Sheet Inputs
A1: Driver | B1: Period 1 | C1: Period 2 | D1: Period 3
A2: Revenue
A3: Direct costs
A4: Operating expenses
A5: Capital spending
A6: Depreciation
A7: Opening cash
A8: Opening fixed assets
A9: Opening debt

Sheet Summary
A1: Statement line | B1: Period 1 | C1: Period 2 | D1: Period 3
A2: Revenue | B2: =Inputs!B2 | C2: =Inputs!C2 | D2: =Inputs!D2
A3: Direct costs | B3: =Inputs!B3 | C3: =Inputs!C3 | D3: =Inputs!D3
A4: Operating expenses | B4: =Inputs!B4 | C4: =Inputs!C4 | D4: =Inputs!D4
A5: Depreciation | B5: =Inputs!B6 | C5: =Inputs!C6 | D5: =Inputs!D6
A6: Net income | B6: =B2-B3-B4-B5 | C6: =C2-C3-C4-C5 | D6: =D2-D3-D4-D5
A7: Operating cash flow | B7: =B6+B5 | C7: =C6+C5 | D7: =D6+D5
A8: Capital spending | B8: =Inputs!B5 | C8: =Inputs!C5 | D8: =Inputs!D5
A9: Closing cash | B9: =Inputs!B7+B7-B8 | C9: =B9+C7-C8 | D9: =C9+D7-D8
A10: Fixed assets | B10: =Inputs!B8+B8-B5 | C10: =B10+C8-C5 | D10: =C10+D8-D5
A11: Total assets | B11: =B9+B10 | C11: =C9+C10 | D11: =D9+D10
A12: Debt | B12: =Inputs!$B$9 | C12: =Inputs!$B$9 | D12: =Inputs!$B$9
A13: Opening equity | B13: =Inputs!$B$7+Inputs!$B$8-Inputs!$B$9 | C13: =Inputs!$B$7+Inputs!$B$8-Inputs!$B$9 | D13: =Inputs!$B$7+Inputs!$B$8-Inputs!$B$9
A14: Retained earnings | B14: =B6 | C14: =B14+C6 | D14: =C14+D6
A15: Total liabilities and equity | B15: =B12+B13+B14 | C15: =C12+C13+C14 | D15: =D12+D13+D14
A16: Balance check | B16: =B11-B15 | C16: =C11-C15 | D16: =D11-D15

Sheet Scope
A1: Simplified example model
A2: Cash sales and cash costs; no tax, working capital, debt changes, or dividends.
A3: Opening balances use Period 1 inputs only. Extend the model for actual requirements.
